{"name": "very_very_valet", "game": "Very Very Valet", "version": "1.0.1", "hidden": false, "groups": [{"name": "Game Options", "options": [{"name": "progression_balancing", "display_name": "Progression Balancing", "description": "A system that can move progression earlier, to try and prevent the player from getting stuck and bored early.\n\nA lower setting means more getting stuck. A higher setting means less getting stuck.", "randomizable": true, "visibility": 15, "type": "NamedRange", "default": 50, "min": 0, "max": 99, "presets": {"disabled": 0, "normal": 50, "extreme": 99}}, {"name": "accessibility", "display_name": "Accessibility", "description": "Set rules for reachability of your items/locations.\n\n**Full:** ensure everything can be reached and acquired.\n\n**Minimal:** ensure what is needed to reach your goal can be acquired.", "randomizable": true, "visibility": 15, "type": "Choice", "default": 0, "choices": [{"name": "full", "display_name": "Full", "value": 0}, {"name": "minimal", "display_name": "Minimal", "value": 2}]}], "collapsed": false}, {"name": "General", "options": [{"name": "limit_stars", "display_name": "Limit Stars", "description": "Prevents required items from being placed on the third star check of each level.", "randomizable": true, "visibility": 15, "type": "Toggle", "default": true}, {"name": "require_red_stars", "display_name": "Require Red Stars", "description": "Determines if red stars (hard mode) are required for checks to send.", "randomizable": true, "visibility": 15, "type": "Toggle", "default": false}, {"name": "require_level_completions", "display_name": "Require Level Completions", "description": "Determines if all levels in each zone must be completed to unlock the final level of the zone.", "randomizable": true, "visibility": 15, "type": "Toggle", "default": false}, {"name": "death_link", "display_name": "Death Link", "description": "When you die, everyone who enabled death link dies. Of course, the reverse is true too.", "randomizable": true, "visibility": 15, "type": "Toggle", "default": false}], "collapsed": false}, {"name": "Item & Location Options", "options": [{"name": "local_items", "display_name": "Local Items", "description": "Forces these items to be in their native world.", "randomizable": false, "visibility": 15, "type": "OptionSet", "default": [], "options": ["Star", "Random Power-Up", "Everything"]}, {"name": "non_local_items", "display_name": "Non-local Items", "description": "Forces these items to be outside their native world.", "randomizable": false, "visibility": 15, "type": "OptionSet", "default": [], "options": ["Star", "Random Power-Up", "Everything"]}, {"name": "start_inventory", "display_name": "Start Inventory", "description": "Start with the specified amount of these items. Example: \"Bomb: 1\"", "randomizable": false, "visibility": 15, "type": "OptionCounter", "default": {}, "min": 0, "max": 10000, "options": ["Star", "Random Power-Up"]}, {"name": "start_hints", "display_name": "Start Hints", "description": "Start with these item's locations prefilled into the ``!hint`` command.", "randomizable": false, "visibility": 15, "type": "OptionSet", "default": [], "options": ["Star", "Random Power-Up", "Everything"]}, {"name": "start_location_hints", "display_name": "Start Location Hints", "description": "Start with these locations and their item prefilled into the ``!hint`` command.", "randomizable": false, "visibility": 15, "type": "OptionSet", "default": [], "options": ["Rooftop Parking - 1 Star", "Rooftop Parking - 2 Stars", "Rooftop Parking - 3 Stars", "Across the Street - 1 Star", "Across the Street - 2 Stars", "Across the Street - 3 Stars", "Alley Avenue - 1 Star", "Alley Avenue - 2 Stars", "Alley Avenue - 3 Stars", "Cliffside Overlook - 1 Star", "Cliffside Overlook - 2 Stars", "Cliffside Overlook - 3 Stars", "Bowled Over - 1 Star", "Bowled Over - 2 Stars", "Bowled Over - 3 Stars", "The Observatory - 1 Star", "The Observatory - 2 Stars", "The Observatory - 3 Stars", "Hotel No Vacancy - 1 Star", "Hotel No Vacancy - 2 Stars", "Hotel No Vacancy - 3 Stars", "Quartz Quarry - 1 Star", "Quartz Quarry - 2 Stars", "Quartz Quarry - 3 Stars", "Up and Down - 1 Star", "Up and Down - 2 Stars", "Up and Down - 3 Stars", "Overpass Galleria - 1 Star", "Overpass Galleria - 2 Stars", "Overpass Galleria - 3 Stars", "Cleanup Crew - 1 Star", "Cleanup Crew - 2 Stars", "Cleanup Crew - 3 Stars", "Now Departing - 1 Star", "Now Departing - 2 Stars", "Now Departing - 3 Stars", "Rinse and Return - 1 Star", "Rinse and Return - 2 Stars", "Rinse and Return - 3 Stars", "Downtown - 1 Star", "Downtown - 2 Stars", "Downtown - 3 Stars", "Macho Motors - 1 Star", "Macho Motors - 2 Stars", "Macho Motors - 3 Stars", "Double Parking - 1 Star", "Double Parking - 2 Stars", "Double Parking - 3 Stars", "Home Sweep Home - 1 Star", "Home Sweep Home - 2 Stars", "Home Sweep Home - 3 Stars", "Seismic Stories - 1 Star", "Seismic Stories - 2 Stars", "Seismic Stories - 3 Stars", "Dueling Venues - 1 Star", "Dueling Venues - 2 Stars", "Dueling Venues - 3 Stars", "The Lot - 1 Star", "The Lot - 2 Stars", "The Lot - 3 Stars", "Sharing Spaces - 1 Star", "Sharing Spaces - 2 Stars", "Sharing Spaces - 3 Stars", "Chaos Caboose - 1 Star", "Chaos Caboose - 2 Stars", "Chaos Caboose - 3 Stars", "Three In One - 1 Star", "Three In One - 2 Stars", "Three In One - 3 Stars", "Everywhere"]}, {"name": "exclude_locations", "display_name": "Excluded Locations", "description": "Prevent these locations from having an important item.", "randomizable": false, "visibility": 15, "type": "OptionSet", "default": [], "options": ["Rooftop Parking - 1 Star", "Rooftop Parking - 2 Stars", "Rooftop Parking - 3 Stars", "Across the Street - 1 Star", "Across the Street - 2 Stars", "Across the Street - 3 Stars", "Alley Avenue - 1 Star", "Alley Avenue - 2 Stars", "Alley Avenue - 3 Stars", "Cliffside Overlook - 1 Star", "Cliffside Overlook - 2 Stars", "Cliffside Overlook - 3 Stars", "Bowled Over - 1 Star", "Bowled Over - 2 Stars", "Bowled Over - 3 Stars", "The Observatory - 1 Star", "The Observatory - 2 Stars", "The Observatory - 3 Stars", "Hotel No Vacancy - 1 Star", "Hotel No Vacancy - 2 Stars", "Hotel No Vacancy - 3 Stars", "Quartz Quarry - 1 Star", "Quartz Quarry - 2 Stars", "Quartz Quarry - 3 Stars", "Up and Down - 1 Star", "Up and Down - 2 Stars", "Up and Down - 3 Stars", "Overpass Galleria - 1 Star", "Overpass Galleria - 2 Stars", "Overpass Galleria - 3 Stars", "Cleanup Crew - 1 Star", "Cleanup Crew - 2 Stars", "Cleanup Crew - 3 Stars", "Now Departing - 1 Star", "Now Departing - 2 Stars", "Now Departing - 3 Stars", "Rinse and Return - 1 Star", "Rinse and Return - 2 Stars", "Rinse and Return - 3 Stars", "Downtown - 1 Star", "Downtown - 2 Stars", "Downtown - 3 Stars", "Macho Motors - 1 Star", "Macho Motors - 2 Stars", "Macho Motors - 3 Stars", "Double Parking - 1 Star", "Double Parking - 2 Stars", "Double Parking - 3 Stars", "Home Sweep Home - 1 Star", "Home Sweep Home - 2 Stars", "Home Sweep Home - 3 Stars", "Seismic Stories - 1 Star", "Seismic Stories - 2 Stars", "Seismic Stories - 3 Stars", "Dueling Venues - 1 Star", "Dueling Venues - 2 Stars", "Dueling Venues - 3 Stars", "The Lot - 1 Star", "The Lot - 2 Stars", "The Lot - 3 Stars", "Sharing Spaces - 1 Star", "Sharing Spaces - 2 Stars", "Sharing Spaces - 3 Stars", "Chaos Caboose - 1 Star", "Chaos Caboose - 2 Stars", "Chaos Caboose - 3 Stars", "Three In One - 1 Star", "Three In One - 2 Stars", "Three In One - 3 Stars", "Everywhere"]}, {"name": "priority_locations", "display_name": "Priority Locations", "description": "Prevent these locations from having an unimportant item.", "randomizable": false, "visibility": 15, "type": "OptionSet", "default": [], "options": ["Rooftop Parking - 1 Star", "Rooftop Parking - 2 Stars", "Rooftop Parking - 3 Stars", "Across the Street - 1 Star", "Across the Street - 2 Stars", "Across the Street - 3 Stars", "Alley Avenue - 1 Star", "Alley Avenue - 2 Stars", "Alley Avenue - 3 Stars", "Cliffside Overlook - 1 Star", "Cliffside Overlook - 2 Stars", "Cliffside Overlook - 3 Stars", "Bowled Over - 1 Star", "Bowled Over - 2 Stars", "Bowled Over - 3 Stars", "The Observatory - 1 Star", "The Observatory - 2 Stars", "The Observatory - 3 Stars", "Hotel No Vacancy - 1 Star", "Hotel No Vacancy - 2 Stars", "Hotel No Vacancy - 3 Stars", "Quartz Quarry - 1 Star", "Quartz Quarry - 2 Stars", "Quartz Quarry - 3 Stars", "Up and Down - 1 Star", "Up and Down - 2 Stars", "Up and Down - 3 Stars", "Overpass Galleria - 1 Star", "Overpass Galleria - 2 Stars", "Overpass Galleria - 3 Stars", "Cleanup Crew - 1 Star", "Cleanup Crew - 2 Stars", "Cleanup Crew - 3 Stars", "Now Departing - 1 Star", "Now Departing - 2 Stars", "Now Departing - 3 Stars", "Rinse and Return - 1 Star", "Rinse and Return - 2 Stars", "Rinse and Return - 3 Stars", "Downtown - 1 Star", "Downtown - 2 Stars", "Downtown - 3 Stars", "Macho Motors - 1 Star", "Macho Motors - 2 Stars", "Macho Motors - 3 Stars", "Double Parking - 1 Star", "Double Parking - 2 Stars", "Double Parking - 3 Stars", "Home Sweep Home - 1 Star", "Home Sweep Home - 2 Stars", "Home Sweep Home - 3 Stars", "Seismic Stories - 1 Star", "Seismic Stories - 2 Stars", "Seismic Stories - 3 Stars", "Dueling Venues - 1 Star", "Dueling Venues - 2 Stars", "Dueling Venues - 3 Stars", "The Lot - 1 Star", "The Lot - 2 Stars", "The Lot - 3 Stars", "Sharing Spaces - 1 Star", "Sharing Spaces - 2 Stars", "Sharing Spaces - 3 Stars", "Chaos Caboose - 1 Star", "Chaos Caboose - 2 Stars", "Chaos Caboose - 3 Stars", "Three In One - 1 Star", "Three In One - 2 Stars", "Three In One - 3 Stars", "Everywhere"]}, {"name": "item_links", "display_name": "Item Links", "description": "Share part of your item pool with other players.", "randomizable": false, "visibility": 13, "type": "Unknown"}, {"name": "plando_items", "display_name": "Plando Items", "description": "Generic items plando.", "randomizable": false, "visibility": 9, "type": "Unknown"}], "collapsed": true}]}